LICENSE
MANIFEST.in
README.rst
requirements.txt
setup.cfg
setup.py
ckanext/__init__.py
ckanext/data_uploader_theme/__init__.py
ckanext/data_uploader_theme/plugin.py
ckanext/data_uploader_theme/public/data_uploader_theme.css
ckanext/data_uploader_theme/templates/base.html
ckanext/data_uploader_theme/templates/home/index.html
ckanext/data_uploader_theme/templates/home/layout1.html
ckanext/data_uploader_theme/templates/home/snippets/promoted.html
ckanext/data_uploader_theme/templates/package/snippets/additional_info.html
ckanext/data_uploader_theme/templates/package/snippets/package_basic_fields.html
ckanext/data_uploader_theme/templates/package/snippets/package_form.html
ckanext/data_uploader_theme/tests/__init__.py
ckanext/data_uploader_theme/tests/test_plugin.py
ckanext_data_uploader_theme.egg-info/PKG-INFO
ckanext_data_uploader_theme.egg-info/SOURCES.txt
ckanext_data_uploader_theme.egg-info/dependency_links.txt
ckanext_data_uploader_theme.egg-info/entry_points.txt
ckanext_data_uploader_theme.egg-info/namespace_packages.txt
ckanext_data_uploader_theme.egg-info/top_level.txt